mdx_wikilink_plus/__init__.py
mdx_wikilink_plus/mdx_wikilink_plus.py
mdx_wikilink_plus/test.py
mdx_wikilink_plus/version.py
mdx_wikilink_plus-1.4.1.dist-info/LICENSE
mdx_wikilink_plus-1.4.1.dist-info/METADATA
mdx_wikilink_plus-1.4.1.dist-info/WHEEL
mdx_wikilink_plus-1.4.1.dist-info/top_level.txt
mdx_wikilink_plus-1.4.1.dist-info/RECORD
