Metadata-Version: 2.1
Name: mdx-wikilink-plus
Version: 1.4.1
Summary: A wikilink extension for Python Markdown
Home-page: https://github.com/neurobin/mdx_wikilink_plus
Author: Md. Jahidul Hamid
Author-email: jahidulhamid@yahoo.com
License: BSD
Keywords: markdown wikilinks wikilink wikilink_plus
Platform: UNKNOWN
Classifier: Development Status :: 5 - Production/Stable
Classifier: Intended Audience :: Developers
Classifier: Intended Audience :: Information Technology
Classifier: License :: OSI Approved :: BSD License
Classifier: Operating System :: OS Independent
Classifier: Programming Language :: Python
Classifier: Programming Language :: Python :: 2
Classifier: Programming Language :: Python :: 3
Classifier: Topic :: Text Processing :: Filters
Classifier: Topic :: Text Processing :: Markup
License-File: LICENSE
